{
  "updated_at": "2026-06-13 18:28",
  "items": [
    {
      "date": "20260613",
      "type": "棚卸し",
      "title": "アプリ構成棚卸し",
      "name": "20260613_棚卸し_アプリ構成棚卸し",
      "summary": "箱は良いが出口(可視化)が無い。配管詰まり2件発見=judgment_log0件・ledger突合0件。iv-input14pxでiOSズーム。📊振り返りタブ提案。",
      "drive_id": "1BZxX5rLo_okwIfMP2stRV-ct6uzfIm-N69XRh--Qlao",
      "drive_url": "https://docs.google.com/document/d/1BZxX5rLo_okwIfMP2stRV-ct6uzfIm-N69XRh--Qlao/edit",
      "created_at": "2026-06-13 18:28"
    },
    {
      "date": "20260611",
      "type": "レポート",
      "title": "現状棚卸し",
      "name": "20260611_レポート_現状棚卸し",
      "summary": "稼働16タスク/停止多数を全件棚卸し。Fable5戦略相談用。課題=落札率10%・8月無人運用(発火信頼性/1Password/死活監視)・クレジット最適化。",
      "drive_id": "1FX0VwFvvfxAKo-ogOVyXYUghO4atb_Dn3d9_qjeKE_s",
      "drive_url": "https://docs.google.com/document/d/1FX0VwFvvfxAKo-ogOVyXYUghO4atb_Dn3d9_qjeKE_s/edit",
      "created_at": "2026-06-11 07:45"
    },
    {
      "date": "20260610",
      "type": "検算",
      "title": "Fable5テスト3カテゴリ",
      "name": "20260610_検算_Fable5テスト3カテゴリ",
      "summary": "ヤフオク3品をFable5検算。レナードカムフォート箱付がTier2粗利22%で本命。Fableは実効コストSonnet比5-6倍→アドホック限定に確定。",
      "drive_id": "1I0m4kWODLPJHCnv50e45h7UExX2ZUgHS7GJxx29k6BM",
      "drive_url": "https://docs.google.com/document/d/1I0m4kWODLPJHCnv50e45h7UExX2ZUgHS7GJxx29k6BM/edit",
      "created_at": "2026-06-10 07:41"
    }
  ]
}